{
	"configurations" : 
	[
		{
			"directories" : 
			[
				{
					"build" : ".",
					"hasInstallRule" : true,
					"jsonFile" : "directory-.-Debug-2cb6088e0657c019f0a1.json",
					"minimumCMakeVersion" : 
					{
						"string" : "3.12"
					},
					"projectIndex" : 0,
					"source" : ".",
					"targetIndexes" : 
					[
						0,
						1,
						2,
						3
					]
				}
			],
			"name" : "Debug",
			"projects" : 
			[
				{
					"directoryIndexes" : 
					[
						0
					],
					"name" : "serial_cpp_pkg",
					"targetIndexes" : 
					[
						0,
						1,
						2,
						3
					]
				}
			],
			"targets" : 
			[
				{
					"directoryIndex" : 0,
					"id" : "Distance_Calculator::@6890427a1f51a3e7e1df",
					"jsonFile" : "target-Distance_Calculator-Debug-e9f74e2effe6c6375b94.json",
					"name" : "Distance_Calculator",
					"projectIndex" : 0
				},
				{
					"directoryIndex" : 0,
					"id" : "Serial_node_1::@6890427a1f51a3e7e1df",
					"jsonFile" : "target-Serial_node_1-Debug-4f018a1fe5a0aeb6490f.json",
					"name" : "Serial_node_1",
					"projectIndex" : 0
				},
				{
					"directoryIndex" : 0,
					"id" : "serial_cpp_pkg_uninstall::@6890427a1f51a3e7e1df",
					"jsonFile" : "target-serial_cpp_pkg_uninstall-Debug-c2a05630cb42f6ad458c.json",
					"name" : "serial_cpp_pkg_uninstall",
					"projectIndex" : 0
				},
				{
					"directoryIndex" : 0,
					"id" : "uninstall::@6890427a1f51a3e7e1df",
					"jsonFile" : "target-uninstall-Debug-4e86b0914b8438a19dd2.json",
					"name" : "uninstall",
					"projectIndex" : 0
				}
			]
		}
	],
	"kind" : "codemodel",
	"paths" : 
	{
		"build" : "/home/einstein/Documents/serial_ws/src/serial_cpp_pkg/build",
		"source" : "/home/einstein/Documents/serial_ws/src/serial_cpp_pkg"
	},
	"version" : 
	{
		"major" : 2,
		"minor" : 3
	}
}
